Workbook

Sheet Inicio
A5: Presupuesto 2027 + Proyección de cierre 2026
A6: Plantilla gratuita de Data Edge · Estado de resultados mensual
B8: Cómo usar esta plantilla
B9: 1. Supuestos | C9: Escribe el nombre de tu empresa y ajusta los porcentajes de crecimiento, inflación, incremento salarial e impuesto.
B10: 2. Cierre 2026 | C10: Reemplaza los datos de ejemplo de enero a septiembre por las cifras reales de tu empresa. Octubre a diciembre se proyectan solos con el promedio de julio a septiembre.
B11: 3. Ajuste de proyección | C11: Si esperas un último trimestre más fuerte o más débil, cambia la columna 'Ajuste Oct-Dic' de cada línea (ej. 10% o -5%).
B12: 4. Presupuesto 2027 | C12: Se calcula automáticamente mes a mes, respetando la estacionalidad de 2026. Puedes cambiar el % de cada línea en la columna 'Incremento %'.
B13: 5. Resumen | C13: Compara cierre 2026 vs. presupuesto 2027 y revisa márgenes y variaciones.
B15: Convención de colores
B16: 1.250.000 | C16: Celda para diligenciar (texto azul, fondo amarillo claro).
B17: 1.250.000 | C17: Fórmula: no la modifiques.
B18: 8,0% | C18: Toma el valor de la hoja Supuestos: puedes sobrescribirlo si lo necesitas.
B20: Los datos que trae la plantilla son de ejemplo: reemplázalos por los de tu empresa.
B22: ¿Necesitas un modelo a la medida?
B23: Diseñamos presupuestos y modelos financieros personalizados para tu empresa, con confidencialidad de tu información.
B24: Escríbenos: info@DataEdgeConsulting.onmicrosoft.com · dataedge-consulting.vercel.app
B26: Herramienta de apoyo para planeación financiera. No reemplaza la asesoría contable o tributaria de tu empresa.
B27: © 2026 Data Edge. Uso permitido dentro de tu empresa; prohibida su reventa o redistribución.

Sheet Supuestos
A5: Supuestos
A6: Ajusta estos valores: alimentan el presupuesto 2027
B8: Supuesto | C8: Valor | D8: Nota
B9: Nombre de la empresa | C9: Mi Empresa S.A.S. | D9: Aparece en el encabezado de las hojas.
B10: Moneda | C10: COP | D10: Moneda en la que registras las cifras.
B11: Crecimiento esperado de ventas 2027 | C11: 0.08 | D11: Valor de ejemplo. Defínelo con tu plan comercial.
B12: Inflación esperada (gastos generales) | C12: 0.045 | D12: Valor de ejemplo. Ajústalo según tus proyecciones o las del mercado.
B13: Incremento salarial 2027 | C13: 0.07 | D13: Valor de ejemplo. Ajústalo cuando se conozca el incremento del salario mínimo.
B14: Tarifa de impuesto de renta | C14: 0.35 | D14: Tarifa general personas jurídicas en Colombia (art. 240 E.T.). Verifica la que aplica a tu empresa.

Sheet Cierre 2026
A5: Proyección de cierre 2026
A6: ="Empresa: "&Empresa&" · Cifras en "&Moneda&" · Ene–Sep real · Oct–Dic proyectado" -> Empresa: Mi Empresa S.A.S. · Cifras en COP · Ene–Sep real · Oct–Dic proyectado
B7: REAL 2026 | K7: PROYECTADO
A8: Concepto | B8: Ene-26 | C8: Feb-26 | D8: Mar-26 | E8: Abr-26 | F8: May-26 | G8: Jun-26 | H8: Jul-26 | I8: Ago-26 | J8: Sep-26 | K8: Oct-26 | L8: Nov-26 | M8: Dic-26 | N8: Total 2026 | O8: Ajuste Oct-Dic
A9: INGRESOS
A10: Ventas / ingresos operacionales | B10: 80000000 | C10: 82000000 | D10: 78000000 | E10: 85000000 | F10: 88000000 | G10: 90000000 | H10: 87000000 | I10: 92000000 | J10: 95000000 | K10: =AVERAGE($H10:$J10)*(1+$O10) -> 91333333 | L10: =AVERAGE($H10:$J10)*(1+$O10) -> 91333333 | M10: =AVERAGE($H10:$J10)*(1+$O10) -> 91333333 | N10: =SUM(B10:M10) -> 1051000000 | O10: 0
A11: Otros ingresos | B11: 1200000 | C11: 1100000 | D11: 1300000 | E11: 1200000 | F11: 1000000 | G11: 1400000 | H11: 1200000 | I11: 1100000 | J11: 1300000 | K11: =AVERAGE($H11:$J11)*(1+$O11) -> 1200000 | L11: =AVERAGE($H11:$J11)*(1+$O11) -> 1200000 | M11: =AVERAGE($H11:$J11)*(1+$O11) -> 1200000 | N11: =SUM(B11:M11) -> 14400000 | O11: 0
A12: Total ingresos | B12: =SUM(B10:B11) -> 81200000 | C12: =SUM(C10:C11) -> 83100000 | D12: =SUM(D10:D11) -> 79300000 | E12: =SUM(E10:E11) -> 86200000 | F12: =SUM(F10:F11) -> 89000000 | G12: =SUM(G10:G11) -> 91400000 | H12: =SUM(H10:H11) -> 88200000 | I12: =SUM(I10:I11) -> 93100000 | ... M12: =SUM(M10:M11) -> 92533333 | N12: =SUM(B12:M12) -> 1065400000
A13: Costo de ventas | B13: 46400000 | C13: 47600000 | D13: 45200000 | E13: 49300000 | F13: 51000000 | G13: 52200000 | H13: 50500000 | I13: 53400000 | J13: 55100000 | K13: =AVERAGE($H13:$J13)*(1+$O13) -> 53000000 | L13: =AVERAGE($H13:$J13)*(1+$O13) -> 53000000 | M13: =AVERAGE($H13:$J13)*(1+$O13) -> 53000000 | N13: =SUM(B13:M13) -> 609700000 | O13: 0
A14: Utilidad bruta | B14: =B12-B13 -> 34800000 | C14: =C12-C13 -> 35500000 | D14: =D12-D13 -> 34100000 | E14: =E12-E13 -> 36900000 | F14: =F12-F13 -> 38000000 | G14: =G12-G13 -> 39200000 | H14: =H12-H13 -> 37700000 | I14: =I12-I13 -> 39700000 | ... M14: =M12-M13 -> 39533333 | N14: =SUM(B14:M14) -> 455700000
A15: Margen bruto % | B15: =IFERROR(B14/B12,0) -> 0.42857143 | C15: =IFERROR(C14/C12,0) -> 0.42719615 | D15: =IFERROR(D14/D12,0) -> 0.43001261 | E15: =IFERROR(E14/E12,0) -> 0.42807425 | F15: =IFERROR(F14/F12,0) -> 0.42696629 | G15: =IFERROR(G14/G12,0) -> 0.42888403 | H15: =IFERROR(H14/H12,0) -> 0.42743764 | I15: =IFERROR(I14/I12,0) -> 0.4264232 | ... N15: =IFERROR(N14/N12,0) -> 0.42772668
A16: GASTOS OPERACIONALES
A17: Nómina y prestaciones | B17: 13500000 | C17: 13500000 | D17: 13500000 | E17: 13500000 | F17: 13500000 | G17: 13500000 | H17: 14200000 | I17: 14200000 | J17: 14200000 | K17: =AVERAGE($H17:$J17)*(1+$O17) -> 14200000 | L17: =AVERAGE($H17:$J17)*(1+$O17) -> 14200000 | M17: =AVERAGE($H17:$J17)*(1+$O17) -> 14200000 | N17: =SUM(B17:M17) -> 166200000 | O17: 0
A18: Arriendos | B18: 4500000 | C18: 4500000 | D18: 4500000 | E18: 4500000 | F18: 4500000 | G18: 4500000 | H18: 4500000 | I18: 4500000 | J18: 4500000 | K18: =AVERAGE($H18:$J18)*(1+$O18) -> 4500000 | L18: =AVERAGE($H18:$J18)*(1+$O18) -> 4500000 | M18: =AVERAGE($H18:$J18)*(1+$O18) -> 4500000 | N18: =SUM(B18:M18) -> 54000000 | O18: 0
A19: Servicios públicos | B19: 1100000 | C19: 1000000 | D19: 1100000 | E19: 1200000 | F19: 1100000 | G19: 1200000 | H19: 1100000 | I19: 1200000 | J19: 1200000 | K19: =AVERAGE($H19:$J19)*(1+$O19) -> 1166666.7 | L19: =AVERAGE($H19:$J19)*(1+$O19) -> 1166666.7 | M19: =AVERAGE($H19:$J19)*(1+$O19) -> 1166666.7 | N19: =SUM(B19:M19) -> 13700000 | O19: 0
A20: Honorarios | B20: 2500000 | C20: 2500000 | D20: 2500000 | E20: 2500000 | F20: 2500000 | G20: 2500000 | H20: 2500000 | I20: 2500000 | J20: 2500000 | K20: =AVERAGE($H20:$J20)*(1+$O20) -> 2500000 | L20: =AVERAGE($H20:$J20)*(1+$O20) -> 2500000 | M20: =AVERAGE($H20:$J20)*(1+$O20) -> 2500000 | N20: =SUM(B20:M20) -> 30000000 | O20: 0
A21: Mercadeo y publicidad | B21: 2000000 | C21: 1800000 | D21: 2200000 | E21: 2000000 | F21: 2500000 | G21: 2000000 | H21: 1900000 | I21: 2100000 | J21: 2400000 | K21: =AVERAGE($H21:$J21)*(1+$O21) -> 2133333.3 | L21: =AVERAGE($H21:$J21)*(1+$O21) -> 2133333.3 | M21: =AVERAGE($H21:$J21)*(1+$O21) -> 2133333.3 | N21: =SUM(B21:M21) -> 25300000 | O21: 0
A22: Tecnología y software | B22: 900000 | C22: 900000 | D22: 900000 | E22: 900000 | F22: 900000 | G22: 900000 | H22: 900000 | I22: 900000 | J22: 900000 | K22: =AVERAGE($H22:$J22)*(1+$O22) -> 900000 | L22: =AVERAGE($H22:$J22)*(1+$O22) -> 900000 | M22: =AVERAGE($H22:$J22)*(1+$O22) -> 900000 | N22: =SUM(B22:M22) -> 10800000 | O22: 0
A23: Depreciaciones y amortizaciones | B23: 1500000 | C23: 1500000 | D23: 1500000 | E23: 1500000 | F23: 1500000 | G23: 1500000 | H23: 1500000 | I23: 1500000 | J23: 1500000 | K23: =AVERAGE($H23:$J23)*(1+$O23) -> 1500000 | L23: =AVERAGE($H23:$J23)*(1+$O23) -> 1500000 | M23: =AVERAGE($H23:$J23)*(1+$O23) -> 1500000 | N23: =SUM(B23:M23) -> 18000000 | O23: 0
A24: Otros gastos operacionales | B24: 1800000 | C24: 1600000 | D24: 1900000 | E24: 1700000 | F24: 1800000 | G24: 2000000 | H24: 1700000 | I24: 1900000 | J24: 1800000 | K24: =AVERAGE($H24:$J24)*(1+$O24) -> 1800000 | L24: =AVERAGE($H24:$J24)*(1+$O24) -> 1800000 | M24: =AVERAGE($H24:$J24)*(1+$O24) -> 1800000 | N24: =SUM(B24:M24) -> 21600000 | O24: 0
A25: Total gastos operacionales | B25: =SUM(B17:B24) -> 27800000 | C25: =SUM(C17:C24) -> 27300000 | D25: =SUM(D17:D24) -> 28100000 | E25: =SUM(E17:E24) -> 27800000 | F25: =SUM(F17:F24) -> 28300000 | G25: =SUM(G17:G24) -> 28100000 | H25: =SUM(H17:H24) -> 28300000 | I25: =SUM(I17:I24) -> 28800000 | ... M25: =SUM(M17:M24) -> 28700000 | N25: =SUM(B25:M25) -> 339600000
A26: Utilidad operacional | B26: =B14-B25 -> 7000000 | C26: =C14-C25 -> 8200000 | D26: =D14-D25 -> 6000000 | E26: =E14-E25 -> 9100000 | F26: =F14-F25 -> 9700000 | G26: =G14-G25 -> 11100000 | H26: =H14-H25 -> 9400000 | I26: =I14-I25 -> 10900000 | ... M26: =M14-M25 -> 10833333 | N26: =SUM(B26:M26) -> 116100000
A27: Gastos financieros | B27: 1200000 | C27: 1200000 | D27: 1200000 | E27: 1150000 | F27: 1150000 | G27: 1100000 | H27: 1100000 | I27: 1050000 | J27: 1050000 | K27: =AVERAGE($H27:$J27)*(1+$O27) -> 1066666.7 | L27: =AVERAGE($H27:$J27)*(1+$O27) -> 1066666.7 | M27: =AVERAGE($H27:$J27)*(1+$O27) -> 1066666.7 | N27: =SUM(B27:M27) -> 13400000 | O27: 0
A28: Utilidad antes de impuestos | B28: =B26-B27 -> 5800000 | C28: =C26-C27 -> 7000000 | D28: =D26-D27 -> 4800000 | E28: =E26-E27 -> 7950000 | F28: =F26-F27 -> 8550000 | G28: =G26-G27 -> 10000000 | H28: =H26-H27 -> 8300000 | I28: =I26-I27 -> 9850000 | ... M28: =M26-M27 -> 9766666.7 | N28: =SUM(B28:M28) -> 102700000
A29: Impuesto de renta estimado | B29: =MAX(0,B28)*Tasa_Renta -> 2030000 | C29: =MAX(0,C28)*Tasa_Renta -> 2450000 | D29: =MAX(0,D28)*Tasa_Renta -> 1680000 | E29: =MAX(0,E28)*Tasa_Renta -> 2782500 | F29: =MAX(0,F28)*Tasa_Renta -> 2992500 | G29: =MAX(0,G28)*Tasa_Renta -> 3500000 | H29: =MAX(0,H28)*Tasa_Renta -> 2905000 | I29: =MAX(0,I28)*Tasa_Renta -> 3447500 | ... M29: =MAX(0,M28)*Tasa_Renta -> 3418333.3 | N29: =SUM(B29:M29) -> 35945000
A30: Utilidad neta | B30: =B28-B29 -> 3770000 | C30: =C28-C29 -> 4550000 | D30: =D28-D29 -> 3120000 | E30: =E28-E29 -> 5167500 | F30: =F28-F29 -> 5557500 | G30: =G28-G29 -> 6500000 | H30: =H28-H29 -> 5395000 | I30: =I28-I29 -> 6402500 | ... M30: =M28-M29 -> 6348333.3 | N30: =SUM(B30:M30) -> 66755000
A31: Margen neto % | B31: =IFERROR(B30/B12,0) -> 0.046428571 | C31: =IFERROR(C30/C12,0) -> 0.054753309 | D31: =IFERROR(D30/D12,0) -> 0.039344262 | E31: =IFERROR(E30/E12,0) -> 0.059947796 | F31: =IFERROR(F30/F12,0) -> 0.06244382 | G31: =IFERROR(G30/G12,0) -> 0.071115974 | H31: =IFERROR(H30/H12,0) -> 0.0611678 | I31: =IFERROR(I30/I12,0) -> 0.06877014 | ... N31: =IFERROR(N30/N12,0) -> 0.062657218

Sheet Presupuesto 2027
A5: Presupuesto 2027
A6: ="Empresa: "&Empresa&" · Cifras en "&Moneda&" · Base: cierre 2026 mes a mes" -> Empresa: Mi Empresa S.A.S. · Cifras en COP · Base: cierre 2026 mes a mes
A8: Concepto | B8: Incremento % | C8: Ene-27 | D8: Feb-27 | E8: Mar-27 | F8: Abr-27 | G8: May-27 | H8: Jun-27 | I8: Jul-27 | J8: Ago-27 | K8: Sep-27 | L8: Oct-27 | M8: Nov-27 | N8: Dic-27 | O8: Total 2027 | P8: Cierre 2026 | Q8: Var. %
A9: INGRESOS
A10: Ventas / ingresos operacionales | B10: =Crec_Ventas -> 0.08 | C10: ='Cierre 2026'!B10*(1+$B10) -> 86400000 | D10: ='Cierre 2026'!C10*(1+$B10) -> 88560000 | E10: ='Cierre 2026'!D10*(1+$B10) -> 84240000 | F10: ='Cierre 2026'!E10*(1+$B10) -> 91800000 | G10: ='Cierre 2026'!F10*(1+$B10) -> 95040000 | H10: ='Cierre 2026'!G10*(1+$B10) -> 97200000 | I10: ='Cierre 2026'!H10*(1+$B10) -> 93960000 | J10: ='Cierre 2026'!I10*(1+$B10) -> 99360000 | ... N10: ='Cierre 2026'!M10*(1+$B10) -> 98640000 | O10: =SUM(C10:N10) -> 1135080000 | P10: ='Cierre 2026'!N10 -> 1051000000 | Q10: =IFERROR(O10/P10-1,0) -> 0.08
A11: Otros ingresos | B11: =Inflacion -> 0.045 | C11: ='Cierre 2026'!B11*(1+$B11) -> 1254000 | D11: ='Cierre 2026'!C11*(1+$B11) -> 1149500 | E11: ='Cierre 2026'!D11*(1+$B11) -> 1358500 | F11: ='Cierre 2026'!E11*(1+$B11) -> 1254000 | G11: ='Cierre 2026'!F11*(1+$B11) -> 1045000 | H11: ='Cierre 2026'!G11*(1+$B11) -> 1463000 | I11: ='Cierre 2026'!H11*(1+$B11) -> 1254000 | J11: ='Cierre 2026'!I11*(1+$B11) -> 1149500 | ... N11: ='Cierre 2026'!M11*(1+$B11) -> 1254000 | O11: =SUM(C11:N11) -> 15048000 | P11: ='Cierre 2026'!N11 -> 14400000 | Q11: =IFERROR(O11/P11-1,0) -> 0.045
A12: Total ingresos | C12: =SUM(C10:C11) -> 87654000 | D12: =SUM(D10:D11) -> 89709500 | E12: =SUM(E10:E11) -> 85598500 | F12: =SUM(F10:F11) -> 93054000 | G12: =SUM(G10:G11) -> 96085000 | H12: =SUM(H10:H11) -> 98663000 | I12: =SUM(I10:I11) -> 95214000 | J12: =SUM(J10:J11) -> 100509500 | ... N12: =SUM(N10:N11) -> 99894000 | O12: =SUM(C12:N12) -> 1150128000 | P12: ='Cierre 2026'!N12 -> 1065400000 | Q12: =IFERROR(O12/P12-1,0) -> 0.079526938
A13: Costo de ventas | B13: =IFERROR('Cierre 2026'!N13/'Cierre 2026'!N10,0) -> 0.58011418 | C13: =C10*$B13 -> 50121865 | D13: =D10*$B13 -> 51374912 | E13: =E10*$B13 -> 48868818 | F13: =F10*$B13 -> 53254481 | G13: =G10*$B13 -> 55134051 | H13: =H10*$B13 -> 56387098 | I13: =I10*$B13 -> 54507528 | J13: =J10*$B13 -> 57640145 | ... N13: =N10*$B13 -> 57222462 | O13: =SUM(C13:N13) -> 658476000 | P13: ='Cierre 2026'!N13 -> 609700000 | Q13: =IFERROR(O13/P13-1,0) -> 0.08
A14: Utilidad bruta | C14: =C12-C13 -> 37532135 | D14: =D12-D13 -> 38334588 | E14: =E12-E13 -> 36729682 | F14: =F12-F13 -> 39799519 | G14: =G12-G13 -> 40950949 | H14: =H12-H13 -> 42275902 | I14: =I12-I13 -> 40706472 | J14: =J12-J13 -> 42869355 | ... N14: =N12-N13 -> 42671538 | O14: =SUM(C14:N14) -> 491652000 | P14: ='Cierre 2026'!N14 -> 455700000 | Q14: =IFERROR(O14/P14-1,0) -> 0.078894009
A15: Margen bruto % | C15: =IFERROR(C14/C12,0) -> 0.42818508 | D15: =IFERROR(D14/D12,0) -> 0.42731916 | E15: =IFERROR(E14/E12,0) -> 0.42909259 | F15: =IFERROR(F14/F12,0) -> 0.42770347 | G15: =IFERROR(G14/G12,0) -> 0.42619502 | H15: =IFERROR(H14/H12,0) -> 0.4284879 | I15: =IFERROR(I14/I12,0) -> 0.42752612 | J15: =IFERROR(J14/J12,0) -> 0.42652043 | ... O15: =IFERROR(O14/O12,0) -> 0.4274759 | P15: ='Cierre 2026'!N15 -> 0.42772668 | Q15: =O15-P15 -> -0.00025077709
A16: GASTOS OPERACIONALES
A17: Nómina y prestaciones | B17: =Incr_Salarial -> 0.07 | C17: ='Cierre 2026'!B17*(1+$B17) -> 14445000 | D17: ='Cierre 2026'!C17*(1+$B17) -> 14445000 | E17: ='Cierre 2026'!D17*(1+$B17) -> 14445000 | F17: ='Cierre 2026'!E17*(1+$B17) -> 14445000 | G17: ='Cierre 2026'!F17*(1+$B17) -> 14445000 | H17: ='Cierre 2026'!G17*(1+$B17) -> 14445000 | I17: ='Cierre 2026'!H17*(1+$B17) -> 15194000 | J17: ='Cierre 2026'!I17*(1+$B17) -> 15194000 | ... N17: ='Cierre 2026'!M17*(1+$B17) -> 15194000 | O17: =SUM(C17:N17) -> 177834000 | P17: ='Cierre 2026'!N17 -> 166200000 | Q17: =IFERROR(O17/P17-1,0) -> 0.07
A18: Arriendos | B18: =Inflacion -> 0.045 | C18: ='Cierre 2026'!B18*(1+$B18) -> 4702500 | D18: ='Cierre 2026'!C18*(1+$B18) -> 4702500 | E18: ='Cierre 2026'!D18*(1+$B18) -> 4702500 | F18: ='Cierre 2026'!E18*(1+$B18) -> 4702500 | G18: ='Cierre 2026'!F18*(1+$B18) -> 4702500 | H18: ='Cierre 2026'!G18*(1+$B18) -> 4702500 | I18: ='Cierre 2026'!H18*(1+$B18) -> 4702500 | J18: ='Cierre 2026'!I18*(1+$B18) -> 4702500 | ... N18: ='Cierre 2026'!M18*(1+$B18) -> 4702500 | O18: =SUM(C18:N18) -> 56430000 | P18: ='Cierre 2026'!N18 -> 54000000 | Q18: =IFERROR(O18/P18-1,0) -> 0.045
A19: Servicios públicos | B19: =Inflacion -> 0.045 | C19: ='Cierre 2026'!B19*(1+$B19) -> 1149500 | D19: ='Cierre 2026'!C19*(1+$B19) -> 1045000 | E19: ='Cierre 2026'!D19*(1+$B19) -> 1149500 | F19: ='Cierre 2026'!E19*(1+$B19) -> 1254000 | G19: ='Cierre 2026'!F19*(1+$B19) -> 1149500 | H19: ='Cierre 2026'!G19*(1+$B19) -> 1254000 | I19: ='Cierre 2026'!H19*(1+$B19) -> 1149500 | J19: ='Cierre 2026'!I19*(1+$B19) -> 1254000 | ... N19: ='Cierre 2026'!M19*(1+$B19) -> 1219166.7 | O19: =SUM(C19:N19) -> 14316500 | P19: ='Cierre 2026'!N19 -> 13700000 | Q19: =IFERROR(O19/P19-1,0) -> 0.045
A20: Honorarios | B20: =Inflacion -> 0.045 | C20: ='Cierre 2026'!B20*(1+$B20) -> 2612500 | D20: ='Cierre 2026'!C20*(1+$B20) -> 2612500 | E20: ='Cierre 2026'!D20*(1+$B20) -> 2612500 | F20: ='Cierre 2026'!E20*(1+$B20) -> 2612500 | G20: ='Cierre 2026'!F20*(1+$B20) -> 2612500 | H20: ='Cierre 2026'!G20*(1+$B20) -> 2612500 | I20: ='Cierre 2026'!H20*(1+$B20) -> 2612500 | J20: ='Cierre 2026'!I20*(1+$B20) -> 2612500 | ... N20: ='Cierre 2026'!M20*(1+$B20) -> 2612500 | O20: =SUM(C20:N20) -> 31350000 | P20: ='Cierre 2026'!N20 -> 30000000 | Q20: =IFERROR(O20/P20-1,0) -> 0.045
A21: Mercadeo y publicidad | B21: =Inflacion -> 0.045 | C21: ='Cierre 2026'!B21*(1+$B21) -> 2090000 | D21: ='Cierre 2026'!C21*(1+$B21) -> 1881000 | E21: ='Cierre 2026'!D21*(1+$B21) -> 2299000 | F21: ='Cierre 2026'!E21*(1+$B21) -> 2090000 | G21: ='Cierre 2026'!F21*(1+$B21) -> 2612500 | H21: ='Cierre 2026'!G21*(1+$B21) -> 2090000 | I21: ='Cierre 2026'!H21*(1+$B21) -> 1985500 | J21: ='Cierre 2026'!I21*(1+$B21) -> 2194500 | ... N21: ='Cierre 2026'!M21*(1+$B21) -> 2229333.3 | O21: =SUM(C21:N21) -> 26438500 | P21: ='Cierre 2026'!N21 -> 25300000 | Q21: =IFERROR(O21/P21-1,0) -> 0.045
A22: Tecnología y software | B22: =Inflacion -> 0.045 | C22: ='Cierre 2026'!B22*(1+$B22) -> 940500 | D22: ='Cierre 2026'!C22*(1+$B22) -> 940500 | E22: ='Cierre 2026'!D22*(1+$B22) -> 940500 | F22: ='Cierre 2026'!E22*(1+$B22) -> 940500 | G22: ='Cierre 2026'!F22*(1+$B22) -> 940500 | H22: ='Cierre 2026'!G22*(1+$B22) -> 940500 | I22: ='Cierre 2026'!H22*(1+$B22) -> 940500 | J22: ='Cierre 2026'!I22*(1+$B22) -> 940500 | ... N22: ='Cierre 2026'!M22*(1+$B22) -> 940500 | O22: =SUM(C22:N22) -> 11286000 | P22: ='Cierre 2026'!N22 -> 10800000 | Q22: =IFERROR(O22/P22-1,0) -> 0.045
A23: Depreciaciones y amortizaciones | B23: 0 | C23: ='Cierre 2026'!B23*(1+$B23) -> 1500000 | D23: ='Cierre 2026'!C23*(1+$B23) -> 1500000 | E23: ='Cierre 2026'!D23*(1+$B23) -> 1500000 | F23: ='Cierre 2026'!E23*(1+$B23) -> 1500000 | G23: ='Cierre 2026'!F23*(1+$B23) -> 1500000 | H23: ='Cierre 2026'!G23*(1+$B23) -> 1500000 | I23: ='Cierre 2026'!H23*(1+$B23) -> 1500000 | J23: ='Cierre 2026'!I23*(1+$B23) -> 1500000 | ... N23: ='Cierre 2026'!M23*(1+$B23) -> 1500000 | O23: =SUM(C23:N23) -> 18000000 | P23: ='Cierre 2026'!N23 -> 18000000 | Q23: =IFERROR(O23/P23-1,0) -> 0
A24: Otros gastos operacionales | B24: =Inflacion -> 0.045 | C24: ='Cierre 2026'!B24*(1+$B24) -> 1881000 | D24: ='Cierre 2026'!C24*(1+$B24) -> 1672000 | E24: ='Cierre 2026'!D24*(1+$B24) -> 1985500 | F24: ='Cierre 2026'!E24*(1+$B24) -> 1776500 | G24: ='Cierre 2026'!F24*(1+$B24) -> 1881000 | H24: ='Cierre 2026'!G24*(1+$B24) -> 2090000 | I24: ='Cierre 2026'!H24*(1+$B24) -> 1776500 | J24: ='Cierre 2026'!I24*(1+$B24) -> 1985500 | ... N24: ='Cierre 2026'!M24*(1+$B24) -> 1881000 | O24: =SUM(C24:N24) -> 22572000 | P24: ='Cierre 2026'!N24 -> 21600000 | Q24: =IFERROR(O24/P24-1,0) -> 0.045
A25: Total gastos operacionales | C25: =SUM(C17:C24) -> 29321000 | D25: =SUM(D17:D24) -> 28798500 | E25: =SUM(E17:E24) -> 29634500 | F25: =SUM(F17:F24) -> 29321000 | G25: =SUM(G17:G24) -> 29843500 | H25: =SUM(H17:H24) -> 29634500 | I25: =SUM(I17:I24) -> 29861000 | J25: =SUM(J17:J24) -> 30383500 | ... N25: =SUM(N17:N24) -> 30279000 | O25: =SUM(C25:N25) -> 358227000 | P25: ='Cierre 2026'!N25 -> 339600000 | Q25: =IFERROR(O25/P25-1,0) -> 0.054849823
A26: Utilidad operacional | C26: =C14-C25 -> 8211135.1 | D26: =D14-D25 -> 9536088.5 | E26: =E14-E25 -> 7095181.7 | F26: =F14-F25 -> 10478519 | G26: =G14-G25 -> 11107449 | H26: =H14-H25 -> 12641402 | I26: =I14-I25 -> 10845472 | J26: =J14-J25 -> 12485855 | ... N26: =N14-N25 -> 12392538 | O26: =SUM(C26:N26) -> 133425000 | P26: ='Cierre 2026'!N26 -> 116100000 | Q26: =IFERROR(O26/P26-1,0) -> 0.14922481
A27: Gastos financieros | B27: 0 | C27: ='Cierre 2026'!B27*(1+$B27) -> 1200000 | D27: ='Cierre 2026'!C27*(1+$B27) -> 1200000 | E27: ='Cierre 2026'!D27*(1+$B27) -> 1200000 | F27: ='Cierre 2026'!E27*(1+$B27) -> 1150000 | G27: ='Cierre 2026'!F27*(1+$B27) -> 1150000 | H27: ='Cierre 2026'!G27*(1+$B27) -> 1100000 | I27: ='Cierre 2026'!H27*(1+$B27) -> 1100000 | J27: ='Cierre 2026'!I27*(1+$B27) -> 1050000 | ... N27: ='Cierre 2026'!M27*(1+$B27) -> 1066666.7 | O27: =SUM(C27:N27) -> 13400000 | P27: ='Cierre 2026'!N27 -> 13400000 | Q27: =IFERROR(O27/P27-1,0) -> 0
A28: Utilidad antes de impuestos | C28: =C26-C27 -> 7011135.1 | D28: =D26-D27 -> 8336088.5 | E28: =E26-E27 -> 5895181.7 | F28: =F26-F27 -> 9328518.6 | G28: =G26-G27 -> 9957448.6 | H28: =H26-H27 -> 11541402 | I28: =I26-I27 -> 9745471.9 | J28: =J26-J27 -> 11435855 | ... N28: =N26-N27 -> 11325871 | O28: =SUM(C28:N28) -> 120025000 | P28: ='Cierre 2026'!N28 -> 102700000 | Q28: =IFERROR(O28/P28-1,0) -> 0.16869523
A29: Impuesto de renta estimado | C29: =MAX(0,C28)*Tasa_Renta -> 2453897.3 | D29: =MAX(0,D28)*Tasa_Renta -> 2917631 | E29: =MAX(0,E28)*Tasa_Renta -> 2063313.6 | F29: =MAX(0,F28)*Tasa_Renta -> 3264981.5 | G29: =MAX(0,G28)*Tasa_Renta -> 3485107 | H29: =MAX(0,H28)*Tasa_Renta -> 4039490.7 | I29: =MAX(0,I28)*Tasa_Renta -> 3410915.2 | J29: =MAX(0,J28)*Tasa_Renta -> 4002549.4 | ... N29: =MAX(0,N28)*Tasa_Renta -> 3964054.8 | O29: =SUM(C29:N29) -> 42008750 | P29: ='Cierre 2026'!N29 -> 35945000 | Q29: =IFERROR(O29/P29-1,0) -> 0.16869523
A30: Utilidad neta | C30: =C28-C29 -> 4557237.8 | D30: =D28-D29 -> 5418457.5 | E30: =E28-E29 -> 3831868.1 | F30: =F28-F29 -> 6063537.1 | G30: =G28-G29 -> 6472341.6 | H30: =H28-H29 -> 7501911.3 | I30: =I28-I29 -> 6334556.8 | J30: =J28-J29 -> 7433306 | ... N30: =N28-N29 -> 7361816.1 | O30: =SUM(C30:N30) -> 78016250 | P30: ='Cierre 2026'!N30 -> 66755000 | Q30: =IFERROR(O30/P30-1,0) -> 0.16869523
A31: Margen neto % | C31: =IFERROR(C30/C12,0) -> 0.051991213 | D31: =IFERROR(D30/D12,0) -> 0.060400041 | E31: =IFERROR(E30/E12,0) -> 0.044765599 | F31: =IFERROR(F30/F12,0) -> 0.065161488 | G31: =IFERROR(G30/G12,0) -> 0.067360583 | H31: =IFERROR(H30/H12,0) -> 0.07603571 | I31: =IFERROR(I30/I12,0) -> 0.066529678 | J31: =IFERROR(J30/J12,0) -> 0.073956253 | ... O31: =IFERROR(O30/O12,0) -> 0.067832667 | P31: ='Cierre 2026'!N31 -> 0.062657218 | Q31: =O31-P31 -> 0.0051754494

Sheet Resumen
A5: Resumen: cierre 2026 vs. presupuesto 2027
A6: ="Empresa: "&Empresa&" · Cifras en "&Moneda -> Empresa: Mi Empresa S.A.S. · Cifras en COP
A8: Concepto | B8: Cierre 2026 | C8: Presupuesto 2027 | D8: Variación
A9: Total ingresos | B9: ='Cierre 2026'!N12 -> 1065400000 | C9: ='Presupuesto 2027'!O12 -> 1150128000 | D9: =IFERROR(C9/B9-1,0) -> 0.079526938
A10: Utilidad bruta | B10: ='Cierre 2026'!N14 -> 455700000 | C10: ='Presupuesto 2027'!O14 -> 491652000 | D10: =IFERROR(C10/B10-1,0) -> 0.078894009
A11: Margen bruto % | B11: ='Cierre 2026'!N15 -> 0.42772668 | C11: ='Presupuesto 2027'!O15 -> 0.4274759 | D11: =C11-B11 -> -0.00025077709
A12: Total gastos operacionales | B12: ='Cierre 2026'!N25 -> 339600000 | C12: ='Presupuesto 2027'!O25 -> 358227000 | D12: =IFERROR(C12/B12-1,0) -> 0.054849823
A13: Utilidad operacional | B13: ='Cierre 2026'!N26 -> 116100000 | C13: ='Presupuesto 2027'!O26 -> 133425000 | D13: =IFERROR(C13/B13-1,0) -> 0.14922481
A14: Utilidad neta | B14: ='Cierre 2026'!N30 -> 66755000 | C14: ='Presupuesto 2027'!O30 -> 78016250 | D14: =IFERROR(C14/B14-1,0) -> 0.16869523
A15: Margen neto % | B15: ='Cierre 2026'!N31 -> 0.062657218 | C15: ='Presupuesto 2027'!O31 -> 0.067832667 | D15: =C15-B15 -> 0.0051754494
A17: Variación de márgenes: diferencia en puntos porcentuales.
A20: Ingresos mensuales
A21: Mes | B21: 2026 | C21: 2027
A22: Ene | B22: ='Cierre 2026'!B12 -> 81200000 | C22: ='Presupuesto 2027'!C12 -> 87654000
A23: Feb | B23: ='Cierre 2026'!C12 -> 83100000 | C23: ='Presupuesto 2027'!D12 -> 89709500
A24: Mar | B24: ='Cierre 2026'!D12 -> 79300000 | C24: ='Presupuesto 2027'!E12 -> 85598500
A25: Abr | B25: ='Cierre 2026'!E12 -> 86200000 | C25: ='Presupuesto 2027'!F12 -> 93054000
A26: May | B26: ='Cierre 2026'!F12 -> 89000000 | C26: ='Presupuesto 2027'!G12 -> 96085000
A27: Jun | B27: ='Cierre 2026'!G12 -> 91400000 | C27: ='Presupuesto 2027'!H12 -> 98663000
A28: Jul | B28: ='Cierre 2026'!H12 -> 88200000 | C28: ='Presupuesto 2027'!I12 -> 95214000
A29: Ago | B29: ='Cierre 2026'!I12 -> 93100000 | C29: ='Presupuesto 2027'!J12 -> 100509500
A30: Sep | B30: ='Cierre 2026'!J12 -> 96300000 | C30: ='Presupuesto 2027'!K12 -> 103958500
A31: Oct | B31: ='Cierre 2026'!K12 -> 92533333 | C31: ='Presupuesto 2027'!L12 -> 99894000
A32: Nov | B32: ='Cierre 2026'!L12 -> 92533333 | C32: ='Presupuesto 2027'!M12 -> 99894000
A33: Dic | B33: ='Cierre 2026'!M12 -> 92533333 | C33: ='Presupuesto 2027'!N12 -> 99894000
