Workbook
Name Anio: Dashboard!$F$6
Name ListaCategorias: Configuración!$H$12:$H$29
Name ListaEgresos: Configuración!$F$12:$F$23
Name ListaIngresos: Configuración!$D$12:$D$17
Name ListaTipo: Configuración!$J$12:$J$13
Name Mes: Dashboard!$E$6
Name SaldoInicial: Configuración!$E$8

Sheet Dashboard
G2: DASHBOARD DE FLUJO DE CAJA | L2: Soporte técnico
G3: Indicadores y análisis del período | L3: info@DataEdgeConsulting.onmicrosoft.com
D5: PERÍODO ACTIVO | E5: MES | F5: AÑO
D6: =TEXT(DATE(Anio,Mes,1),"mmmm yyyy") -> noviembre 2026 | E6: 11 | F6: 2026
D8: INGRESOS DEL MES | E8: EGRESOS DEL MES | F8: FLUJO NETO | G8: SALDO FINAL
D9: =SUMIFS(tblMov[Ingreso],tblMov[Fecha],">="&DATE(Anio,Mes,1),tblMov[Fecha],"<="&EOMONTH(DATE(Anio,Mes,1),0)) -> 8500 | E9: =SUMIFS(tblMov[Egreso],tblMov[Fecha],">="&DATE(Anio,Mes,1),tblMov[Fecha],"<="&EOMONTH(DATE(Anio,Mes,1),0)) -> 240 | F9: =D9-E9 -> 8260 | G9: =SaldoInicial+F9 -> 9260
D11: Día / Fecha | E11: Ingresos | F11: Egresos | G11: Saldo acumulado
D12: =IF(MONTH(DATE(Anio,Mes,ROW()-11))=Mes,DATE(Anio,Mes,ROW()-11),"") -> 46327 | E12: =IF(D12="","",SUMIFS(tblMov[Ingreso],tblMov[Fecha],D12)) -> 3500 | F12: =IF(D12="","",SUMIFS(tblMov[Egreso],tblMov[Fecha],D12)) -> 0 | G12: =IF(D12="","",SaldoInicial+SUMIFS(tblMov[Ingreso],tblMov[Fecha],"<="&D12,tblMov[Fecha],">="&DATE(Anio,Mes,1))-SUMIFS(tblMov[Egreso],tblMov[Fecha],"<="&D12,tblMov[Fecha],">="&DATE(Anio,Mes,1))) -> 4500
D13: =IF(MONTH(DATE(Anio,Mes,ROW()-11))=Mes,DATE(Anio,Mes,ROW()-11),"") -> 46328 | E13: =IF(D13="","",SUMIFS(tblMov[Ingreso],tblMov[Fecha],D13)) -> 0 | F13: =IF(D13="","",SUMIFS(tblMov[Egreso],tblMov[Fecha],D13)) -> 180 | G13: =IF(D13="","",SaldoInicial+SUMIFS(tblMov[Ingreso],tblMov[Fecha],"<="&D13,tblMov[Fecha],">="&DATE(Anio,Mes,1))-SUMIFS(tblMov[Egreso],tblMov[Fecha],"<="&D13,tblMov[Fecha],">="&DATE(Anio,Mes,1))) -> 4320
D14: =IF(MONTH(DATE(Anio,Mes,ROW()-11))=Mes,DATE(Anio,Mes,ROW()-11),"") -> 46329 | E14: =IF(D14="","",SUMIFS(tblMov[Ingreso],tblMov[Fecha],D14)) -> 5000 | F14: =IF(D14="","",SUMIFS(tblMov[Egreso],tblMov[Fecha],D14)) -> 60 | G14: =IF(D14="","",SaldoInicial+SUMIFS(tblMov[Ingreso],tblMov[Fecha],"<="&D14,tblMov[Fecha],">="&DATE(Anio,Mes,1))-SUMIFS(tblMov[Egreso],tblMov[Fecha],"<="&D14,tblMov[Fecha],">="&DATE(Anio,Mes,1))) -> 9260
D15: =IF(MONTH(DATE(Anio,Mes,ROW()-11))=Mes,DATE(Anio,Mes,ROW()-11),"") -> 46330 | E15: =IF(D15="","",SUMIFS(tblMov[Ingreso],tblMov[Fecha],D15)) -> 0 | F15: =IF(D15="","",SUMIFS(tblMov[Egreso],tblMov[Fecha],D15)) -> 0 | G15: =IF(D15="","",SaldoInicial+SUMIFS(tblMov[Ingreso],tblMov[Fecha],"<="&D15,tblMov[Fecha],">="&DATE(Anio,Mes,1))-SUMIFS(tblMov[Egreso],tblMov[Fecha],"<="&D15,tblMov[Fecha],">="&DATE(Anio,Mes,1))) -> 9260
D16: =IF(MONTH(DATE(Anio,Mes,ROW()-11))=Mes,DATE(Anio,Mes,ROW()-11),"") -> 46331 | E16: =IF(D16="","",SUMIFS(tblMov[Ingreso],tblMov[Fecha],D16)) -> 0 | F16: =IF(D16="","",SUMIFS(tblMov[Egreso],tblMov[Fecha],D16)) -> 0 | G16: =IF(D16="","",SaldoInicial+SUMIFS(tblMov[Ingreso],tblMov[Fecha],"<="&D16,tblMov[Fecha],">="&DATE(Anio,Mes,1))-SUMIFS(tblMov[Egreso],tblMov[Fecha],"<="&D16,tblMov[Fecha],">="&DATE(Anio,Mes,1))) -> 9260
D17: =IF(MONTH(DATE(Anio,Mes,ROW()-11))=Mes,DATE(Anio,Mes,ROW()-11),"") -> 46332 | E17: =IF(D17="","",SUMIFS(tblMov[Ingreso],tblMov[Fecha],D17)) -> 0 | F17: =IF(D17="","",SUMIFS(tblMov[Egreso],tblMov[Fecha],D17)) -> 0 | G17: =IF(D17="","",SaldoInicial+SUMIFS(tblMov[Ingreso],tblMov[Fecha],"<="&D17,tblMov[Fecha],">="&DATE(Anio,Mes,1))-SUMIFS(tblMov[Egreso],tblMov[Fecha],"<="&D17,tblMov[Fecha],">="&DATE(Anio,Mes,1))) -> 9260
D18: =IF(MONTH(DATE(Anio,Mes,ROW()-11))=Mes,DATE(Anio,Mes,ROW()-11),"") -> 46333 | E18: =IF(D18="","",SUMIFS(tblMov[Ingreso],tblMov[Fecha],D18)) -> 0 | F18: =IF(D18="","",SUMIFS(tblMov[Egreso],tblMov[Fecha],D18)) -> 0 | G18: =IF(D18="","",SaldoInicial+SUMIFS(tblMov[Ingreso],tblMov[Fecha],"<="&D18,tblMov[Fecha],">="&DATE(Anio,Mes,1))-SUMIFS(tblMov[Egreso],tblMov[Fecha],"<="&D18,tblMov[Fecha],">="&DATE(Anio,Mes,1))) -> 9260
D19: =IF(MONTH(DATE(Anio,Mes,ROW()-11))=Mes,DATE(Anio,Mes,ROW()-11),"") -> 46334 | E19: =IF(D19="","",SUMIFS(tblMov[Ingreso],tblMov[Fecha],D19)) -> 0 | F19: =IF(D19="","",SUMIFS(tblMov[Egreso],tblMov[Fecha],D19)) -> 0 | G19: =IF(D19="","",SaldoInicial+SUMIFS(tblMov[Ingreso],tblMov[Fecha],"<="&D19,tblMov[Fecha],">="&DATE(Anio,Mes,1))-SUMIFS(tblMov[Egreso],tblMov[Fecha],"<="&D19,tblMov[Fecha],">="&DATE(Anio,Mes,1))) -> 9260
D20: =IF(MONTH(DATE(Anio,Mes,ROW()-11))=Mes,DATE(Anio,Mes,ROW()-11),"") -> 46335 | E20: =IF(D20="","",SUMIFS(tblMov[Ingreso],tblMov[Fecha],D20)) -> 0 | F20: =IF(D20="","",SUMIFS(tblMov[Egreso],tblMov[Fecha],D20)) -> 0 | G20: =IF(D20="","",SaldoInicial+SUMIFS(tblMov[Ingreso],tblMov[Fecha],"<="&D20,tblMov[Fecha],">="&DATE(Anio,Mes,1))-SUMIFS(tblMov[Egreso],tblMov[Fecha],"<="&D20,tblMov[Fecha],">="&DATE(Anio,Mes,1))) -> 9260
D21: =IF(MONTH(DATE(Anio,Mes,ROW()-11))=Mes,DATE(Anio,Mes,ROW()-11),"") -> 46336 | E21: =IF(D21="","",SUMIFS(tblMov[Ingreso],tblMov[Fecha],D21)) -> 0 | F21: =IF(D21="","",SUMIFS(tblMov[Egreso],tblMov[Fecha],D21)) -> 0 | G21: =IF(D21="","",SaldoInicial+SUMIFS(tblMov[Ingreso],tblMov[Fecha],"<="&D21,tblMov[Fecha],">="&DATE(Anio,Mes,1))-SUMIFS(tblMov[Egreso],tblMov[Fecha],"<="&D21,tblMov[Fecha],">="&DATE(Anio,Mes,1))) -> 9260
D22: =IF(MONTH(DATE(Anio,Mes,ROW()-11))=Mes,DATE(Anio,Mes,ROW()-11),"") -> 46337 | E22: =IF(D22="","",SUMIFS(tblMov[Ingreso],tblMov[Fecha],D22)) -> 0 | F22: =IF(D22="","",SUMIFS(tblMov[Egreso],tblMov[Fecha],D22)) -> 0 | G22: =IF(D22="","",SaldoInicial+SUMIFS(tblMov[Ingreso],tblMov[Fecha],"<="&D22,tblMov[Fecha],">="&DATE(Anio,Mes,1))-SUMIFS(tblMov[Egreso],tblMov[Fecha],"<="&D22,tblMov[Fecha],">="&DATE(Anio,Mes,1))) -> 9260
D23: =IF(MONTH(DATE(Anio,Mes,ROW()-11))=Mes,DATE(Anio,Mes,ROW()-11),"") -> 46338 | E23: =IF(D23="","",SUMIFS(tblMov[Ingreso],tblMov[Fecha],D23)) -> 0 | F23: =IF(D23="","",SUMIFS(tblMov[Egreso],tblMov[Fecha],D23)) -> 0 | G23: =IF(D23="","",SaldoInicial+SUMIFS(tblMov[Ingreso],tblMov[Fecha],"<="&D23,tblMov[Fecha],">="&DATE(Anio,Mes,1))-SUMIFS(tblMov[Egreso],tblMov[Fecha],"<="&D23,tblMov[Fecha],">="&DATE(Anio,Mes,1))) -> 9260
... D42: =IF(MONTH(DATE(Anio,Mes,ROW()-11))=Mes,DATE(Anio,Mes,ROW()-11),"") | E42: =IF(D42="","",SUMIFS(tblMov[Ingreso],tblMov[Fecha],D42)) | F42: =IF(D42="","",SUMIFS(tblMov[Egreso],tblMov[Fecha],D42)) | G42: =IF(D42="","",SaldoInicial+SUMIFS(tblMov[Ingreso],tblMov[Fecha],"<="&D42,tblMov[Fecha],">="&DATE(Anio,Mes,1))-SUMIFS(tblMov[Egreso],tblMov[Fecha],"<="&D42,tblMov[Fecha],">="&DATE(Anio,Mes,1)))

Sheet Tablas
D2: TABLAS DE SOPORTE | M2: info@DataEdgeConsulting.onmicrosoft.com
D3: Datos calculados que alimentan los gráficos del Dashboard | M3: Soporte y consultas
D6: RESUMEN MES A MES (AÑO ACTUAL) | I6: TOP 5 CATEGORÍAS DE GASTO (MES ACTUAL)
D7: Mes | E7: Ingresos | F7: Egresos | I7: # | J7: Categoría | K7: Total | M7: Categoría | N7: Total
D8: =TEXT(DATE(Anio,1,1),"mmm") -> ene | E8: =SUMIFS(tblMov[Ingreso],tblMov[Fecha],">="&DATE(Anio,1,1),tblMov[Fecha],"<="&EOMONTH(DATE(Anio,1,1),0)) -> 0 | F8: =SUMIFS(tblMov[Egreso],tblMov[Fecha],">="&DATE(Anio,1,1),tblMov[Fecha],"<="&EOMONTH(DATE(Anio,1,1),0)) -> 0 | I8: 1 | J8: =IF(IFERROR(LARGE($N$8:$N$19,1),-1)<=0,"",IFERROR(INDEX($M$8:$M$19,MATCH(LARGE($N$8:$N$19,1),$N$8:$N$19,0)),"")) -> Proveedores | K8: =IFERROR(IF(LARGE($N$8:$N$19,1)<=0,0,ROUND(LARGE($N$8:$N$19,1),2)),0) -> 180 | M8: =Configuración!F12 -> Proveedores | N8: =SUMIFS(tblMov[Egreso],tblMov[Categoría],M8,tblMov[Fecha],">="&DATE(Anio,Mes,1),tblMov[Fecha],"<="&EOMONTH(DATE(Anio,Mes,1),0))-ROW()/1000000 -> 179.99999
D9: =TEXT(DATE(Anio,2,1),"mmm") -> feb | E9: =SUMIFS(tblMov[Ingreso],tblMov[Fecha],">="&DATE(Anio,2,1),tblMov[Fecha],"<="&EOMONTH(DATE(Anio,2,1),0)) -> 0 | F9: =SUMIFS(tblMov[Egreso],tblMov[Fecha],">="&DATE(Anio,2,1),tblMov[Fecha],"<="&EOMONTH(DATE(Anio,2,1),0)) -> 0 | I9: 2 | J9: =IF(IFERROR(LARGE($N$8:$N$19,2),-1)<=0,"",IFERROR(INDEX($M$8:$M$19,MATCH(LARGE($N$8:$N$19,2),$N$8:$N$19,0)),"")) -> Transporte y fletes | K9: =IFERROR(IF(LARGE($N$8:$N$19,2)<=0,0,ROUND(LARGE($N$8:$N$19,2),2)),0) -> 60 | M9: =Configuración!F13 -> Transporte y fletes | N9: =SUMIFS(tblMov[Egreso],tblMov[Categoría],M9,tblMov[Fecha],">="&DATE(Anio,Mes,1),tblMov[Fecha],"<="&EOMONTH(DATE(Anio,Mes,1),0))-ROW()/1000000 -> 59.999991
D10: =TEXT(DATE(Anio,3,1),"mmm") -> mar | E10: =SUMIFS(tblMov[Ingreso],tblMov[Fecha],">="&DATE(Anio,3,1),tblMov[Fecha],"<="&EOMONTH(DATE(Anio,3,1),0)) -> 0 | F10: =SUMIFS(tblMov[Egreso],tblMov[Fecha],">="&DATE(Anio,3,1),tblMov[Fecha],"<="&EOMONTH(DATE(Anio,3,1),0)) -> 0 | I10: 3 | J10: =IF(IFERROR(LARGE($N$8:$N$19,3),-1)<=0,"",IFERROR(INDEX($M$8:$M$19,MATCH(LARGE($N$8:$N$19,3),$N$8:$N$19,0)),"")) | K10: =IFERROR(IF(LARGE($N$8:$N$19,3)<=0,0,ROUND(LARGE($N$8:$N$19,3),2)),0) -> 0 | M10: =Configuración!F14 -> Arriendo | N10: =SUMIFS(tblMov[Egreso],tblMov[Categoría],M10,tblMov[Fecha],">="&DATE(Anio,Mes,1),tblMov[Fecha],"<="&EOMONTH(DATE(Anio,Mes,1),0))-ROW()/1000000 -> -1e-05
D11: =TEXT(DATE(Anio,4,1),"mmm") -> abr | E11: =SUMIFS(tblMov[Ingreso],tblMov[Fecha],">="&DATE(Anio,4,1),tblMov[Fecha],"<="&EOMONTH(DATE(Anio,4,1),0)) -> 0 | F11: =SUMIFS(tblMov[Egreso],tblMov[Fecha],">="&DATE(Anio,4,1),tblMov[Fecha],"<="&EOMONTH(DATE(Anio,4,1),0)) -> 0 | I11: 4 | J11: =IF(IFERROR(LARGE($N$8:$N$19,4),-1)<=0,"",IFERROR(INDEX($M$8:$M$19,MATCH(LARGE($N$8:$N$19,4),$N$8:$N$19,0)),"")) | K11: =IFERROR(IF(LARGE($N$8:$N$19,4)<=0,0,ROUND(LARGE($N$8:$N$19,4),2)),0) -> 0 | M11: =Configuración!F15 -> Servicios públicos | N11: =SUMIFS(tblMov[Egreso],tblMov[Categoría],M11,tblMov[Fecha],">="&DATE(Anio,Mes,1),tblMov[Fecha],"<="&EOMONTH(DATE(Anio,Mes,1),0))-ROW()/1000000 -> -1.1e-05
D12: =TEXT(DATE(Anio,5,1),"mmm") -> may | E12: =SUMIFS(tblMov[Ingreso],tblMov[Fecha],">="&DATE(Anio,5,1),tblMov[Fecha],"<="&EOMONTH(DATE(Anio,5,1),0)) -> 0 | F12: =SUMIFS(tblMov[Egreso],tblMov[Fecha],">="&DATE(Anio,5,1),tblMov[Fecha],"<="&EOMONTH(DATE(Anio,5,1),0)) -> 0 | I12: 5 | J12: =IF(IFERROR(LARGE($N$8:$N$19,5),-1)<=0,"",IFERROR(INDEX($M$8:$M$19,MATCH(LARGE($N$8:$N$19,5),$N$8:$N$19,0)),"")) | K12: =IFERROR(IF(LARGE($N$8:$N$19,5)<=0,0,ROUND(LARGE($N$8:$N$19,5),2)),0) -> 0 | M12: =Configuración!F16 -> Internet y telefonía | N12: =SUMIFS(tblMov[Egreso],tblMov[Categoría],M12,tblMov[Fecha],">="&DATE(Anio,Mes,1),tblMov[Fecha],"<="&EOMONTH(DATE(Anio,Mes,1),0))-ROW()/1000000 -> -1.2e-05
D13: =TEXT(DATE(Anio,6,1),"mmm") -> jun | E13: =SUMIFS(tblMov[Ingreso],tblMov[Fecha],">="&DATE(Anio,6,1),tblMov[Fecha],"<="&EOMONTH(DATE(Anio,6,1),0)) -> 0 | F13: =SUMIFS(tblMov[Egreso],tblMov[Fecha],">="&DATE(Anio,6,1),tblMov[Fecha],"<="&EOMONTH(DATE(Anio,6,1),0)) -> 0 | M13: =Configuración!F17 -> Seguridad social | N13: =SUMIFS(tblMov[Egreso],tblMov[Categoría],M13,tblMov[Fecha],">="&DATE(Anio,Mes,1),tblMov[Fecha],"<="&EOMONTH(DATE(Anio,Mes,1),0))-ROW()/1000000 -> -1.3e-05
D14: =TEXT(DATE(Anio,7,1),"mmm") -> jul | E14: =SUMIFS(tblMov[Ingreso],tblMov[Fecha],">="&DATE(Anio,7,1),tblMov[Fecha],"<="&EOMONTH(DATE(Anio,7,1),0)) -> 0 | F14: =SUMIFS(tblMov[Egreso],tblMov[Fecha],">="&DATE(Anio,7,1),tblMov[Fecha],"<="&EOMONTH(DATE(Anio,7,1),0)) -> 0 | M14: =Configuración!F18 -> Nómina | N14: =SUMIFS(tblMov[Egreso],tblMov[Categoría],M14,tblMov[Fecha],">="&DATE(Anio,Mes,1),tblMov[Fecha],"<="&EOMONTH(DATE(Anio,Mes,1),0))-ROW()/1000000 -> -1.4e-05
D15: =TEXT(DATE(Anio,8,1),"mmm") -> ago | E15: =SUMIFS(tblMov[Ingreso],tblMov[Fecha],">="&DATE(Anio,8,1),tblMov[Fecha],"<="&EOMONTH(DATE(Anio,8,1),0)) -> 0 | F15: =SUMIFS(tblMov[Egreso],tblMov[Fecha],">="&DATE(Anio,8,1),tblMov[Fecha],"<="&EOMONTH(DATE(Anio,8,1),0)) -> 0 | M15: =Configuración!F19 -> Impuestos | N15: =SUMIFS(tblMov[Egreso],tblMov[Categoría],M15,tblMov[Fecha],">="&DATE(Anio,Mes,1),tblMov[Fecha],"<="&EOMONTH(DATE(Anio,Mes,1),0))-ROW()/1000000 -> -1.5e-05
D16: =TEXT(DATE(Anio,9,1),"mmm") -> sep | E16: =SUMIFS(tblMov[Ingreso],tblMov[Fecha],">="&DATE(Anio,9,1),tblMov[Fecha],"<="&EOMONTH(DATE(Anio,9,1),0)) -> 0 | F16: =SUMIFS(tblMov[Egreso],tblMov[Fecha],">="&DATE(Anio,9,1),tblMov[Fecha],"<="&EOMONTH(DATE(Anio,9,1),0)) -> 0 | M16: =Configuración!F20 -> Publicidad y mercadeo | N16: =SUMIFS(tblMov[Egreso],tblMov[Categoría],M16,tblMov[Fecha],">="&DATE(Anio,Mes,1),tblMov[Fecha],"<="&EOMONTH(DATE(Anio,Mes,1),0))-ROW()/1000000 -> -1.6e-05
D17: =TEXT(DATE(Anio,10,1),"mmm") -> oct | E17: =SUMIFS(tblMov[Ingreso],tblMov[Fecha],">="&DATE(Anio,10,1),tblMov[Fecha],"<="&EOMONTH(DATE(Anio,10,1),0)) -> 0 | F17: =SUMIFS(tblMov[Egreso],tblMov[Fecha],">="&DATE(Anio,10,1),tblMov[Fecha],"<="&EOMONTH(DATE(Anio,10,1),0)) -> 0 | M17: =Configuración!F21 -> Compra de equipos | N17: =SUMIFS(tblMov[Egreso],tblMov[Categoría],M17,tblMov[Fecha],">="&DATE(Anio,Mes,1),tblMov[Fecha],"<="&EOMONTH(DATE(Anio,Mes,1),0))-ROW()/1000000 -> -1.7e-05
D18: =TEXT(DATE(Anio,11,1),"mmm") -> nov | E18: =SUMIFS(tblMov[Ingreso],tblMov[Fecha],">="&DATE(Anio,11,1),tblMov[Fecha],"<="&EOMONTH(DATE(Anio,11,1),0)) -> 8500 | F18: =SUMIFS(tblMov[Egreso],tblMov[Fecha],">="&DATE(Anio,11,1),tblMov[Fecha],"<="&EOMONTH(DATE(Anio,11,1),0)) -> 240 | M18: =Configuración!F22 -> Pago de créditos | N18: =SUMIFS(tblMov[Egreso],tblMov[Categoría],M18,tblMov[Fecha],">="&DATE(Anio,Mes,1),tblMov[Fecha],"<="&EOMONTH(DATE(Anio,Mes,1),0))-ROW()/1000000 -> -1.8e-05
D19: =TEXT(DATE(Anio,12,1),"mmm") -> dic | E19: =SUMIFS(tblMov[Ingreso],tblMov[Fecha],">="&DATE(Anio,12,1),tblMov[Fecha],"<="&EOMONTH(DATE(Anio,12,1),0)) -> 0 | F19: =SUMIFS(tblMov[Egreso],tblMov[Fecha],">="&DATE(Anio,12,1),tblMov[Fecha],"<="&EOMONTH(DATE(Anio,12,1),0)) -> 0 | M19: =Configuración!F23 -> Otros gastos | N19: =SUMIFS(tblMov[Egreso],tblMov[Categoría],M19,tblMov[Fecha],">="&DATE(Anio,Mes,1),tblMov[Fecha],"<="&EOMONTH(DATE(Anio,Mes,1),0))-ROW()/1000000 -> -1.9e-05

Sheet Movimientos
G2: REGISTRO DE MOVIMIENTOS | L2: Soporte técnico
G3: Captura diaria de ingresos y egresos | L3: info@DataEdgeConsulting.onmicrosoft.com
B5: Captura de movimientos
B6: Fecha | C6: Tipo | D6: Categoría | E6: Descripción | F6: Ingreso | G6: Egreso | H6: Saldo del día
B7: 46327 | C7: Ingreso | D7: Ventas de contado | E7: Venta de contado del día | F7: 3500 | H7: =IF(tblMov[[#This Row],[Fecha]]="","",SaldoInicial+SUMIFS(tblMov[Ingreso],tblMov[Fecha],"<="&tblMov[[#This Row],[Fecha]])-SUMIFS(tblMov[Egreso],tblMov[Fecha],"<="&tblMov[[#This Row],[Fecha]])) -> 4500
B8: 46328 | C8: Egreso | D8: Proveedores | E8: Pago a proveedor de insumos | G8: 180 | H8: =IF(tblMov[[#This Row],[Fecha]]="","",SaldoInicial+SUMIFS(tblMov[Ingreso],tblMov[Fecha],"<="&tblMov[[#This Row],[Fecha]])-SUMIFS(tblMov[Egreso],tblMov[Fecha],"<="&tblMov[[#This Row],[Fecha]])) -> 4320
B9: 46329 | C9: Egreso | D9: Transporte y fletes | E9: Flete de despacho | G9: 60 | H9: =IF(tblMov[[#This Row],[Fecha]]="","",SaldoInicial+SUMIFS(tblMov[Ingreso],tblMov[Fecha],"<="&tblMov[[#This Row],[Fecha]])-SUMIFS(tblMov[Egreso],tblMov[Fecha],"<="&tblMov[[#This Row],[Fecha]])) -> 9260
B10: 46329 | C10: Ingreso | D10: Otros ingresos | E10: Ingreso no operacional | F10: 5000 | H10: =IF(tblMov[[#This Row],[Fecha]]="","",SaldoInicial+SUMIFS(tblMov[Ingreso],tblMov[Fecha],"<="&tblMov[[#This Row],[Fecha]])-SUMIFS(tblMov[Egreso],tblMov[Fecha],"<="&tblMov[[#This Row],[Fecha]])) -> 9260
H11: =IF(tblMov[[#This Row],[Fecha]]="","",SaldoInicial+SUMIFS(tblMov[Ingreso],tblMov[Fecha],"<="&tblMov[[#This Row],[Fecha]])-SUMIFS(tblMov[Egreso],tblMov[Fecha],"<="&tblMov[[#This Row],[Fecha]]))
H12: =IF(tblMov[[#This Row],[Fecha]]="","",SaldoInicial+SUMIFS(tblMov[Ingreso],tblMov[Fecha],"<="&tblMov[[#This Row],[Fecha]])-SUMIFS(tblMov[Egreso],tblMov[Fecha],"<="&tblMov[[#This Row],[Fecha]]))
H13: =IF(tblMov[[#This Row],[Fecha]]="","",SaldoInicial+SUMIFS(tblMov[Ingreso],tblMov[Fecha],"<="&tblMov[[#This Row],[Fecha]])-SUMIFS(tblMov[Egreso],tblMov[Fecha],"<="&tblMov[[#This Row],[Fecha]]))
H14: =IF(tblMov[[#This Row],[Fecha]]="","",SaldoInicial+SUMIFS(tblMov[Ingreso],tblMov[Fecha],"<="&tblMov[[#This Row],[Fecha]])-SUMIFS(tblMov[Egreso],tblMov[Fecha],"<="&tblMov[[#This Row],[Fecha]]))
H15: =IF(tblMov[[#This Row],[Fecha]]="","",SaldoInicial+SUMIFS(tblMov[Ingreso],tblMov[Fecha],"<="&tblMov[[#This Row],[Fecha]])-SUMIFS(tblMov[Egreso],tblMov[Fecha],"<="&tblMov[[#This Row],[Fecha]]))
H16: =IF(tblMov[[#This Row],[Fecha]]="","",SaldoInicial+SUMIFS(tblMov[Ingreso],tblMov[Fecha],"<="&tblMov[[#This Row],[Fecha]])-SUMIFS(tblMov[Egreso],tblMov[Fecha],"<="&tblMov[[#This Row],[Fecha]]))
H17: =IF(tblMov[[#This Row],[Fecha]]="","",SaldoInicial+SUMIFS(tblMov[Ingreso],tblMov[Fecha],"<="&tblMov[[#This Row],[Fecha]])-SUMIFS(tblMov[Egreso],tblMov[Fecha],"<="&tblMov[[#This Row],[Fecha]]))
H18: =IF(tblMov[[#This Row],[Fecha]]="","",SaldoInicial+SUMIFS(tblMov[Ingreso],tblMov[Fecha],"<="&tblMov[[#This Row],[Fecha]])-SUMIFS(tblMov[Egreso],tblMov[Fecha],"<="&tblMov[[#This Row],[Fecha]]))
H19: =IF(tblMov[[#This Row],[Fecha]]="","",SaldoInicial+SUMIFS(tblMov[Ingreso],tblMov[Fecha],"<="&tblMov[[#This Row],[Fecha]])-SUMIFS(tblMov[Egreso],tblMov[Fecha],"<="&tblMov[[#This Row],[Fecha]]))
H20: =IF(tblMov[[#This Row],[Fecha]]="","",SaldoInicial+SUMIFS(tblMov[Ingreso],tblMov[Fecha],"<="&tblMov[[#This Row],[Fecha]])-SUMIFS(tblMov[Egreso],tblMov[Fecha],"<="&tblMov[[#This Row],[Fecha]]))
H21: =IF(tblMov[[#This Row],[Fecha]]="","",SaldoInicial+SUMIFS(tblMov[Ingreso],tblMov[Fecha],"<="&tblMov[[#This Row],[Fecha]])-SUMIFS(tblMov[Egreso],tblMov[Fecha],"<="&tblMov[[#This Row],[Fecha]]))
H22: =IF(tblMov[[#This Row],[Fecha]]="","",SaldoInicial+SUMIFS(tblMov[Ingreso],tblMov[Fecha],"<="&tblMov[[#This Row],[Fecha]])-SUMIFS(tblMov[Egreso],tblMov[Fecha],"<="&tblMov[[#This Row],[Fecha]]))
... H66: =IF(tblMov[[#This Row],[Fecha]]="","",SaldoInicial+SUMIFS(tblMov[Ingreso],tblMov[Fecha],"<="&tblMov[[#This Row],[Fecha]])-SUMIFS(tblMov[Egreso],tblMov[Fecha],"<="&tblMov[[#This Row],[Fecha]]))
B202: Sugerencia: registra cada movimiento en la fecha real. El saldo se calcula automáticamente.

Sheet Configuración
G2: PANEL DE CONFIGURACIÓN | L2: Soporte técnico
G3: Parámetros y categorías editables | L3: info@DataEdgeConsulting.onmicrosoft.com
D5: Parámetro | E5: Valor
D6: Mes (1-12) | E6: =Mes -> 11
D7: Año | E7: =Anio -> 2026
D8: Saldo inicial | E8: 1000
D11: Categorías de Ingresos | F11: Categorías de Egresos | H11: Todas las categorías | J11: Tipo
D12: Ventas de contado | F12: Proveedores | H12: Ventas de contado | J12: Ingreso
D13: Cobro de cartera | F13: Transporte y fletes | H13: Cobro de cartera | J13: Egreso
D14: Anticipos de clientes | F14: Arriendo | H14: Anticipos de clientes
D15: Rendimientos financieros | F15: Servicios públicos | H15: Rendimientos financieros
D16: Préstamos recibidos | F16: Internet y telefonía | H16: Préstamos recibidos
D17: Otros ingresos | F17: Seguridad social | H17: Otros ingresos
F18: Nómina | H18: Proveedores
F19: Impuestos | H19: Transporte y fletes
F20: Publicidad y mercadeo | H20: Arriendo
F21: Compra de equipos | H21: Servicios públicos
F22: Pago de créditos | H22: Internet y telefonía
F23: Otros gastos | H23: Seguridad social
H24: Nómina
H25: Impuestos
H26: Publicidad y mercadeo
H27: Compra de equipos
H28: Pago de créditos
H29: Otros gastos
D31: Nota: estos parámetros alimentan automáticamente las hojas Movimientos y Dashboard.
